fuzzywuzzy-stubs/__init__.pyi
fuzzywuzzy-stubs/fuzz.pyi
fuzzywuzzy-stubs/process.pyi
fuzzywuzzy-stubs/string_processing.pyi
fuzzywuzzy-stubs/utils.pyi
fuzzywuzzy_stubs-0.0.1.dist-info/LICENSE
fuzzywuzzy_stubs-0.0.1.dist-info/METADATA
fuzzywuzzy_stubs-0.0.1.dist-info/WHEEL
fuzzywuzzy_stubs-0.0.1.dist-info/top_level.txt
fuzzywuzzy_stubs-0.0.1.dist-info/RECORD
