Metadata-Version: 2.1
Name: fuzzywuzzy-stubs
Version: 0.0.1
Summary: fuzzywuzzy stubs and mypy plugin
Home-page: https://github.com/5uper5hoot/fuzzywuzzy-stubs
Author: Peter Schutt
Author-email: peter@topsport.com.au
License: GPL
Platform: UNKNOWN
Classifier: Development Status :: 3 - Alpha
Classifier: Programming Language :: Python :: 3
Requires-Dist: mypy
